jsonvalue2markdown.py
jsonvalue2markdown-0.0.1.dist-info/LICENSE
jsonvalue2markdown-0.0.1.dist-info/METADATA
jsonvalue2markdown-0.0.1.dist-info/WHEEL
jsonvalue2markdown-0.0.1.dist-info/top_level.txt
jsonvalue2markdown-0.0.1.dist-info/RECORD
