Metadata-Version: 2.1
Name: jsonvalue2markdown
Version: 0.0.1
Summary: Convert json value to markdown
Home-page: https://github.com/snjyor/jsonvalue2markdown
Author: snjyor
Author-email: snjyor@163.com
License: MIT
Platform: UNKNOWN
License-File: LICENSE
